django_tst_cms/__init__.py
django_tst_cms/admin.py
django_tst_cms/models.py
django_tst_cms/tests.py
django_tst_cms/urls.py
django_tst_cms/views.py
django_tst_cms/management/__init__.py
django_tst_cms/management/commands/__init__.py
django_tst_cms/management/commands/fix_permissions.py
django_tst_cms/migrations/__init__.py
django_tst_cms/static/__init__.py
django_tst_cms/static/admin/css/base.css
django_tst_cms/static/admin/css/changelists.css
django_tst_cms/static/admin/css/dashboard.css
django_tst_cms/static/admin/css/fonts.css
django_tst_cms/static/admin/css/forms.css
django_tst_cms/static/admin/css/login.css
django_tst_cms/static/admin/css/rtl.css
django_tst_cms/static/admin/css/widgets.css
django_tst_cms/static/admin/fonts/LICENSE.txt
django_tst_cms/static/admin/fonts/README.txt
django_tst_cms/static/admin/fonts/Roboto-Bold-webfont.woff
django_tst_cms/static/admin/fonts/Roboto-Light-webfont.woff
django_tst_cms/static/admin/fonts/Roboto-Regular-webfont.woff
django_tst_cms/static/admin/img/LICENSE
django_tst_cms/static/admin/img/README.txt
django_tst_cms/static/admin/img/calendar-icons.svg
django_tst_cms/static/admin/img/icon-addlink.svg
django_tst_cms/static/admin/img/icon-alert.svg
django_tst_cms/static/admin/img/icon-calendar.svg
django_tst_cms/static/admin/img/icon-changelink.svg
django_tst_cms/static/admin/img/icon-clock.svg
django_tst_cms/static/admin/img/icon-deletelink.svg
django_tst_cms/static/admin/img/icon-no.svg
django_tst_cms/static/admin/img/icon-unknown-alt.svg
django_tst_cms/static/admin/img/icon-unknown.svg
django_tst_cms/static/admin/img/icon-yes.svg
django_tst_cms/static/admin/img/inline-delete.svg
django_tst_cms/static/admin/img/search.svg
django_tst_cms/static/admin/img/selector-icons.svg
django_tst_cms/static/admin/img/sorting-icons.svg
django_tst_cms/static/admin/img/tooltag-add.svg
django_tst_cms/static/admin/img/tooltag-arrowright.svg
django_tst_cms/static/admin/img/gis/move_vertex_off.svg
django_tst_cms-1.5.0.dist-info/LICENSE.txt
django_tst_cms-1.5.0.dist-info/METADATA
django_tst_cms-1.5.0.dist-info/WHEEL
django_tst_cms-1.5.0.dist-info/top_level.txt
django_tst_cms-1.5.0.dist-info/RECORD
